reusegen/__init__.py
reusegen-0.1.2.dist-info/LICENSE
reusegen-0.1.2.dist-info/METADATA
reusegen-0.1.2.dist-info/WHEEL
reusegen-0.1.2.dist-info/top_level.txt
reusegen-0.1.2.dist-info/RECORD
