Metadata-Version: 2.1
Name: reusegen
Version: 0.1.2
Summary: Cache generator's results and reuse them
Home-page: http://github.com/whoiscc/reusegen
Author: Correctizer
Author-email: correctizer@gmail.com
License: MIT
Platform: UNKNOWN
Classifier: Development Status :: 3 - Alpha
Classifier: License :: OSI Approved :: MIT License
Classifier: Programming Language :: Python :: 3.7
Classifier: Topic :: Utilities
